gamoto/__init__.py
gamoto/admin.py
gamoto/apps.py
gamoto/ca.py
gamoto/forms.py
gamoto/iptables.py
gamoto/models.py
gamoto/openvpn.py
gamoto/settings.py
gamoto/urls.py
gamoto/users.py
gamoto/views.py
gamoto/wsgi.py
gamoto/management/__init__.py
gamoto/management/commands/__init__.py
gamoto/management/commands/_private.py
gamoto/management/commands/gamudo.py
gamoto/management/commands/makeadmin.py
gamoto/management/commands/openvpn.py
gamoto/management/commands/setup.py
gamoto/migrations/__init__.py
gamoto/static/main.css
gamoto/static/qrcode.min.js
gamoto/templates/.base.html.swp
gamoto/templates/admin_endpoints.html
gamoto/templates/admin_group_create.html
gamoto/templates/admin_host_add.html
gamoto/templates/admin_subnet_add.html
gamoto/templates/admin_subnet_create.html
gamoto/templates/admin_users.html
gamoto/templates/base.html
gamoto/templates/enroll.html
gamoto/templates/index.html
gamoto/templates/login.html
gamoto/templates/user_group_modify.html
gamoto/tests/__init__.py
gamoto/tests/data.py
gamoto/tests/test_gamoto.py
gamoto-0.0.18.data/scripts/gamoto
gamoto-0.0.18.dist-info/METADATA
gamoto-0.0.18.dist-info/WHEEL
gamoto-0.0.18.dist-info/top_level.txt
gamoto-0.0.18.dist-info/RECORD
