Metadata-Version: 2.1
Name: gamoto
Version: 0.0.18
Summary: A web portal for VPN self service
Home-page: http://github.com/calston/gamoto
Author: Colin Alston
Author-email: colin.alston@gmail.com
License: BSD
Platform: UNKNOWN
Classifier: Programming Language :: Python
Requires-Dist: pyopenssl
Requires-Dist: django (>=2.2.3)
Requires-Dist: social-auth-app-django
Requires-Dist: pyotp
Requires-Dist: gunicorn
Requires-Dist: django-crispy-forms
